ai_scholar_toolbox/Scholar78kSearch.py
ai_scholar_toolbox/ScholarGsSearch.py
ai_scholar_toolbox/ScholarSearch.py
ai_scholar_toolbox/__init__.py
ai_scholar_toolbox-0.0.1.dist-info/LICENSE
ai_scholar_toolbox-0.0.1.dist-info/METADATA
ai_scholar_toolbox-0.0.1.dist-info/WHEEL
ai_scholar_toolbox-0.0.1.dist-info/top_level.txt
ai_scholar_toolbox-0.0.1.dist-info/RECORD
