Metadata-Version: 2.1
Name: ai-scholar-toolbox
Version: 0.0.1
Summary: Find Google Scholar Profiles
Home-page: https://github.com/causalNLP/ai-scholar-toolbox
Author: 
License: MIT
Classifier: Programming Language :: Python
Classifier: Programming Language :: Python :: 3.6
Classifier: Programming Language :: Python :: 3.7
Classifier: Programming Language :: Python :: 3.8
Classifier: License :: OSI Approved :: MIT License
Classifier: Operating System :: OS Independent
Requires-Python: >=3.7
License-File: LICENSE
Requires-Dist: gdown
Requires-Dist: bs4
Requires-Dist: selenium
Requires-Dist: pandas
Requires-Dist: requests
Requires-Dist: numpy
